ya_tracker_client/__init__.py
ya_tracker_client/py.typed
ya_tracker_client/domain/client/__init__.py
ya_tracker_client/domain/client/base.py
ya_tracker_client/domain/client/errors.py
ya_tracker_client/domain/entities/__init__.py
ya_tracker_client/domain/entities/action.py
ya_tracker_client/domain/entities/attachment.py
ya_tracker_client/domain/entities/base.py
ya_tracker_client/domain/entities/bulk_operation.py
ya_tracker_client/domain/entities/calendar.py
ya_tracker_client/domain/entities/checklist.py
ya_tracker_client/domain/entities/comment.py
ya_tracker_client/domain/entities/component.py
ya_tracker_client/domain/entities/deadline.py
ya_tracker_client/domain/entities/duration.py
ya_tracker_client/domain/entities/external_application.py
ya_tracker_client/domain/entities/external_link.py
ya_tracker_client/domain/entities/external_object.py
ya_tracker_client/domain/entities/issue.py
ya_tracker_client/domain/entities/issue_change_history.py
ya_tracker_client/domain/entities/issue_field.py
ya_tracker_client/domain/entities/issue_relationship.py
ya_tracker_client/domain/entities/issue_status.py
ya_tracker_client/domain/entities/issue_type.py
ya_tracker_client/domain/entities/issue_type_config.py
ya_tracker_client/domain/entities/macro.py
ya_tracker_client/domain/entities/mailing_list.py
ya_tracker_client/domain/entities/priority.py
ya_tracker_client/domain/entities/project.py
ya_tracker_client/domain/entities/queue.py
ya_tracker_client/domain/entities/queue_autoaction.py
ya_tracker_client/domain/entities/queue_field.py
ya_tracker_client/domain/entities/queue_field_category.py
ya_tracker_client/domain/entities/queue_field_options_provider.py
ya_tracker_client/domain/entities/queue_field_query_provider.py
ya_tracker_client/domain/entities/queue_field_schema.py
ya_tracker_client/domain/entities/queue_field_suggest_provider.py
ya_tracker_client/domain/entities/queue_version.py
ya_tracker_client/domain/entities/resolution.py
ya_tracker_client/domain/entities/sprint.py
ya_tracker_client-0.1.0.dist-info/licenses/LICENSE
ya_tracker_client-0.1.0.dist-info/METADATA
ya_tracker_client-0.1.0.dist-info/WHEEL
ya_tracker_client-0.1.0.dist-info/top_level.txt
ya_tracker_client-0.1.0.dist-info/RECORD
