Metadata-Version: 2.4
Name: ya_tracker_client
Version: 0.1.0
Summary: Async Yandex Tracker Client
Author-email: Дмитрий Анфимов <work@danfimov.ru>
License: MIT License
Project-URL: Bug Tracker, https://github.com/danfimov/ya_tracker_client/issues
Project-URL: Repository, https://github.com/danfimov/ya_tracker_client/
Keywords: Yandex,Tracker,API,async
Classifier: Development Status :: 5 - Production/Stable
Classifier: Intended Audience :: Developers
Classifier: Framework :: AsyncIO
Classifier: License :: OSI Approved :: MIT License
Classifier: Programming Language :: Python
Classifier: Programming Language :: Python :: 3.10
Classifier: Programming Language :: Python :: 3.11
Classifier: Programming Language :: Python :: 3.12
Classifier: Programming Language :: Python :: 3.13
Classifier: Programming Language :: Python :: Implementation :: CPython
Classifier: Topic :: Software Development :: Libraries :: Application Frameworks
Classifier: Typing :: Typed
Requires-Python: <=3.14,>=3.10
License-File: LICENSE
Requires-Dist: aiohttp>=3.8.5
Requires-Dist: pydantic>=1.10.21
Requires-Dist: certifi>=2023.7.22
Requires-Dist: requests>=2.31.0
Dynamic: license-file
